<?xml version="1.0" encoding="UTF-8"?>

<Bundle xmlns="http://hl7.org/fhir">
  <id value="EMLA-2525-Plaster-SE-AJ"/>
  <type value="batch"/>
  <entry>
    <fullUrl value="{$base}/MedicinalProductDefinition/EMLA-2525-Plaster-SE-AJ-MedicinalProductDefinition"/>
    <resource>
      <MedicinalProductDefinition>
        <id value="EMLA-2525-Plaster-SE-AJ-MedicinalProductDefinition"/>
        <text>
          <status value="generated"/><div xmlns="http://www.w3.org/1999/xhtml"><p><b>Generated Narrative: MedicinalProductDefinition</b><a name="EMLA-2525-Plaster-SE-AJ-MedicinalProductDefinition"> </a></p><div style="display: inline-block; background-color: #d9e0e7; padding: 6px; margin: 4px; border: 1px solid #8da1b4; border-radius: 5px; line-height: 60%"><p style="margin-bottom: 0px">Resource MedicinalProductDefinition &quot;EMLA-2525-Plaster-SE-AJ-MedicinalProductDefinition&quot; </p></div><p><b>identifier</b>: id: SE-100001718-00011834, id: 1867</p><p><b>domain</b>: Human use <span style="background: LightGoldenRodYellow; margin: 4px; border: 1px solid khaki"> (100000000004#100000000012)</span></p><p><b>status</b>: Current <span style="background: LightGoldenRodYellow; margin: 4px; border: 1px solid khaki"> (200000005003#200000005004)</span></p><p><b>indication</b>: Emla plåster används vid: • Ytanestesi av intakt hud i samband med: o nålstick, t.ex. vid inläggning av perifer venkateter eller vid blodprovstagning o ytliga kirurgiska ingrepp, hos vuxna och den pediatriska populationen</p><p><b>legalStatusOfSupply</b>: Medicinal product subject to medical prescription exempt for some pack sizes <span style="background: LightGoldenRodYellow; margin: 4px; border: 1px solid khaki"> (100000072051#200000002239)</span></p><p><b>classification</b>: N01BB20 <span style="background: LightGoldenRodYellow; margin: 4px; border: 1px solid khaki"> (100000093533#100000097205)</span></p><blockquote><p><b>name</b></p><p><b>productName</b>: EMLA 25 mg/25 mg Medicinskt plåster</p><blockquote><p><b>namePart</b></p><p><b>part</b>: EMLA</p><p><b>type</b>: Invented Name Part <span style="background: LightGoldenRodYellow; margin: 4px; border: 1px solid khaki"> (220000000000#220000000002)</span></p></blockquote><blockquote><p><b>namePart</b></p><p><b>part</b>: 25 mg/25 mg</p><p><b>type</b>: Strength part <span style="background: LightGoldenRodYellow; margin: 4px; border: 1px solid khaki"> (220000000000#220000000004)</span></p></blockquote><blockquote><p><b>namePart</b></p><p><b>part</b>: Medicinskt plåster</p><p><b>type</b>: Pharmaceutical dose form part <span style="background: LightGoldenRodYellow; margin: 4px; border: 1px solid khaki"> (220000000000#220000000005)</span></p></blockquote><h3>CountryLanguages</h3><table class="grid"><tr><td>-</td><td><b>Country</b></td><td><b>Language</b></td></tr><tr><td>*</td><td>Sweden <span style="background: LightGoldenRodYellow; margin: 4px; border: 1px solid khaki"> (100000000002#100000000535)</span></td><td>Swedish <span style="background: LightGoldenRodYellow; margin: 4px; border: 1px solid khaki"> (100000072057#100000072288)</span></td></tr></table></blockquote></div>
        </text>
        <extension url="http://ema.europa.eu/fhir/extension/authorisedDoseForm">
          <valueCoding>
            <system value="http://spor.ema.europa.eu/v1/lists/200000000004"/>
            <code value="100000073714"/>
            <display value="Medicated plaster"/>
          </valueCoding>
        </extension>
        <identifier>
          <system value="http://ema.europa.eu/fhir/mpId"/>
          <value value="SE-100001718-00011834"/>
        </identifier>
        <identifier>
          <system value="http://ema.europa.eu/fhir/eurdId"/>
          <value value="1867"/>
        </identifier>
        <domain>
          <coding>
            <system value="http://spor.ema.europa.eu/v1/lists/100000000004"/>
            <code value="100000000012"/>
            <display value="Human use"/>
          </coding>
        </domain>
        <status>
          <coding>
            <system value="http://spor.ema.europa.eu/v1/lists/200000005003"/>
            <code value="200000005004"/>
            <display value="Current"/>
          </coding>
        </status>
        <indication value="Emla plåster används vid: • Ytanestesi av intakt hud i samband med: o nålstick, t.ex. vid inläggning av perifer venkateter eller vid blodprovstagning o ytliga kirurgiska ingrepp, hos vuxna och den pediatriska populationen"/>
        <legalStatusOfSupply>
          <coding>
            <system value="http://spor.ema.europa.eu/v1/lists/100000072051"/>
            <code value="200000002239"/>
            <display value="Medicinal product subject to medical prescription exempt for some pack sizes"/>
          </coding>
        </legalStatusOfSupply>
        <classification>
          <coding>
            <system value="http://spor.ema.europa.eu/v1/lists/100000093533"/>
            <code value="100000097205"/>
            <display value="N01BB20"/>
          </coding>
        </classification>
        <name>
          <productName value="EMLA 25 mg/25 mg Medicinskt plåster"/>
          <namePart>
            <part value="EMLA"/>
            <type>
              <coding>
                <system value="http://spor.ema.europa.eu/v1/lists/220000000000"/>
                <code value="220000000002"/>
                <display value="Invented Name Part"/>
              </coding>
            </type>
          </namePart>
          <namePart>
            <part value="25 mg/25 mg"/>
            <type>
              <coding>
                <system value="http://spor.ema.europa.eu/v1/lists/220000000000"/>
                <code value="220000000004"/>
                <display value="Strength part"/>
              </coding>
            </type>
          </namePart>
          <namePart>
            <part value="Medicinskt plåster"/>
            <type>
              <coding>
                <system value="http://spor.ema.europa.eu/v1/lists/220000000000"/>
                <code value="220000000005"/>
                <display value="Pharmaceutical dose form part"/>
              </coding>
            </type>
          </namePart>
          <countryLanguage>
            <country>
              <coding>
                <system value="http://spor.ema.europa.eu/v1/lists/100000000002"/>
                <code value="100000000535"/>
                <display value="Sweden"/>
              </coding>
            </country>
            <language>
              <coding>
                <system value="http://spor.ema.europa.eu/v1/lists/100000072057"/>
                <code value="100000072288"/>
                <display value="Swedish"/>
              </coding>
            </language>
          </countryLanguage>
        </name>
      </MedicinalProductDefinition>
    </resource>
    <request>
      <method value="POST"/>
      <url value="MedicinalProductDefinition/EMLA-2525-Plaster-SE-AJ-MedicinalProductDefinition"/>
    </request>
  </entry>
  <entry>
    <fullUrl value="{$base}/RegulatedAuthorization/EMLA-2525-Plaster-SE-AJ-RegulatedAuthorization"/>
    <resource>
      <RegulatedAuthorization>
        <id value="EMLA-2525-Plaster-SE-AJ-RegulatedAuthorization"/>
        <text>
          <status value="generated"/><div xmlns="http://www.w3.org/1999/xhtml"><p><b>Generated Narrative: RegulatedAuthorization</b><a name="EMLA-2525-Plaster-SE-AJ-RegulatedAuthorization"> </a></p><div style="display: inline-block; background-color: #d9e0e7; padding: 6px; margin: 4px; border: 1px solid #8da1b4; border-radius: 5px; line-height: 60%"><p style="margin-bottom: 0px">Resource RegulatedAuthorization &quot;EMLA-2525-Plaster-SE-AJ-RegulatedAuthorization&quot; </p></div><p><b>identifier</b>: id: 11834</p><p><b>subject</b>: <a href="#MedicinalProductDefinition_EMLA-2525-Plaster-SE-AJ-MedicinalProductDefinition">See above (MedicinalProductDefinition/EMLA-2525-Plaster-SE-AJ-MedicinalProductDefinition)</a></p><p><b>type</b>: Marketing Authorisation <span style="background: LightGoldenRodYellow; margin: 4px; border: 1px solid khaki"> (220000000060#220000000061)</span></p><p><b>region</b>: Sweden <span style="background: LightGoldenRodYellow; margin: 4px; border: 1px solid khaki"> (100000000002#100000000535)</span></p><p><b>status</b>: Valid <span style="background: LightGoldenRodYellow; margin: 4px; border: 1px solid khaki"> (100000072049#100000072099)</span></p><p><b>statusDate</b>: 1993-05-28</p><p><b>holder</b>: <span>: Aspen Pharma Trading Limited</span></p><h3>Cases</h3><table class="grid"><tr><td>-</td><td><b>Type</b></td><td><b>Date[x]</b></td></tr><tr><td>*</td><td>First Authorisation <span style="background: LightGoldenRodYellow; margin: 4px; border: 1px solid khaki"> (authorisationDateType#dateOfFirstAuthorisation)</span></td><td>1993-05-28</td></tr></table></div>
        </text>
        <identifier>
          <system value="http://ema.europa.eu/fhir/MarketingAuthorizationNumber"/>
          <value value="11834"/>
        </identifier>
        <subject>
          <reference value="MedicinalProductDefinition/EMLA-2525-Plaster-SE-AJ-MedicinalProductDefinition"/>
        </subject>
        <type>
          <coding>
            <system value="http://spor.ema.europa.eu/v1/lists/220000000060"/>
            <code value="220000000061"/>
            <display value="Marketing Authorisation"/>
          </coding>
        </type>
        <region>
          <coding>
            <system value="http://spor.ema.europa.eu/v1/lists/100000000002"/>
            <code value="100000000535"/>
            <display value="Sweden"/>
          </coding>
        </region>
        <status>
          <coding>
            <system value="http://spor.ema.europa.eu/v1/lists/100000072049"/>
            <code value="100000072099"/>
            <display value="Valid"/>
          </coding>
        </status>
        <statusDate value="1993-05-28"/>
        <holder>
          <identifier>
            <system value="https://spor.ema.europa.eu/v1/locations"/>
            <value value="LOC-100001575"/>
          </identifier>
          <display value="Aspen Pharma Trading Limited"/>
        </holder>
        <case>
          <type>
            <coding>
              <system value="http://ema.europa.eu/fhir/authorisationDateType"/>
              <code value="dateOfFirstAuthorisation"/>
              <display value="First Authorisation"/>
            </coding>
          </type>
          <dateDateTime value="1993-05-28"/>
        </case>
      </RegulatedAuthorization>
    </resource>
    <request>
      <method value="POST"/>
      <url value="RegulatedAuthorization/EMLA-2525-Plaster-SE-AJ-RegulatedAuthorization"/>
    </request>
  </entry>
  <entry>
    <fullUrl value="{$base}/AdministrableProductDefinition/EMLA-2525-Plaster-SE-AJ-AdministrableProductDefinition"/>
    <resource>
      <AdministrableProductDefinition>
        <id value="EMLA-2525-Plaster-SE-AJ-AdministrableProductDefinition"/>
        <text>
          <status value="generated"/><div xmlns="http://www.w3.org/1999/xhtml"><p><b>Generated Narrative: AdministrableProductDefinition</b><a name="EMLA-2525-Plaster-SE-AJ-AdministrableProductDefinition"> </a></p><div style="display: inline-block; background-color: #d9e0e7; padding: 6px; margin: 4px; border: 1px solid #8da1b4; border-radius: 5px; line-height: 60%"><p style="margin-bottom: 0px">Resource AdministrableProductDefinition &quot;EMLA-2525-Plaster-SE-AJ-AdministrableProductDefinition&quot; </p></div><p><b>status</b>: active</p><p><b>formOf</b>: <a href="#MedicinalProductDefinition_EMLA-2525-Plaster-SE-AJ-MedicinalProductDefinition">See above (MedicinalProductDefinition/EMLA-2525-Plaster-SE-AJ-MedicinalProductDefinition)</a></p><p><b>administrableDoseForm</b>: Medicated plaster <span style="background: LightGoldenRodYellow; margin: 4px; border: 1px solid khaki"> (200000000004#100000073714)</span></p><p><b>producedFrom</b>: <a href="#ManufacturedItemDefinition_EMLA-2525-Plaster-SE-AJ-ManufacturedItemDefinition">See above (ManufacturedItemDefinition/EMLA-2525-Plaster-SE-AJ-ManufacturedItemDefinition)</a></p><h3>RouteOfAdministrations</h3><table class="grid"><tr><td>-</td><td><b>Code</b></td></tr><tr><td>*</td><td>Cutaneous use <span style="background: LightGoldenRodYellow; margin: 4px; border: 1px solid khaki"> (100000073345#100000073566)</span></td></tr></table></div>
        </text>
        <status value="active"/>
        <formOf>
          <reference value="MedicinalProductDefinition/EMLA-2525-Plaster-SE-AJ-MedicinalProductDefinition"/>
        </formOf>
        <administrableDoseForm>
          <coding>
            <system value="http://spor.ema.europa.eu/v1/lists/200000000004"/>
            <code value="100000073714"/>
            <display value="Medicated plaster"/>
          </coding>
        </administrableDoseForm>
        <producedFrom>
          <reference value="ManufacturedItemDefinition/EMLA-2525-Plaster-SE-AJ-ManufacturedItemDefinition"/>
        </producedFrom>
        <routeOfAdministration>
          <code>
            <coding>
              <system value="http://spor.ema.europa.eu/v1/lists/100000073345"/>
              <code value="100000073566"/>
              <display value="Cutaneous use"/>
            </coding>
          </code>
        </routeOfAdministration>
      </AdministrableProductDefinition>
    </resource>
    <request>
      <method value="POST"/>
      <url value="AdministrableProductDefinition/EMLA-2525-Plaster-SE-AJ-AdministrableProductDefinition"/>
    </request>
  </entry>
  <entry>
    <fullUrl value="{$base}/PackagedProductDefinition/EMLA-2525-Plaster-SE-AJ-PackagedProductDefinition01"/>
    <resource>
      <PackagedProductDefinition>
        <id value="EMLA-2525-Plaster-SE-AJ-PackagedProductDefinition01"/>
        <text>
          <status value="generated"/><div xmlns="http://www.w3.org/1999/xhtml"><p><b>Generated Narrative: PackagedProductDefinition</b><a name="EMLA-2525-Plaster-SE-AJ-PackagedProductDefinition01"> </a></p><div style="display: inline-block; background-color: #d9e0e7; padding: 6px; margin: 4px; border: 1px solid #8da1b4; border-radius: 5px; line-height: 60%"><p style="margin-bottom: 0px">Resource PackagedProductDefinition &quot;EMLA-2525-Plaster-SE-AJ-PackagedProductDefinition01&quot; </p></div><p><b>packageFor</b>: <a href="#MedicinalProductDefinition_EMLA-2525-Plaster-SE-AJ-MedicinalProductDefinition">See above (MedicinalProductDefinition/EMLA-2525-Plaster-SE-AJ-MedicinalProductDefinition)</a></p><p><b>description</b>: Påse, 2 x 1 plåster</p><h3>MarketingStatuses</h3><table class="grid"><tr><td>-</td><td><b>Country</b></td><td><b>Status</b></td></tr><tr><td>*</td><td>Sweden <span style="background: LightGoldenRodYellow; margin: 4px; border: 1px solid khaki"> (100000000002#100000000535)</span></td><td>Marketed <span style="background: LightGoldenRodYellow; margin: 4px; border: 1px solid khaki"> (100000072052#100000072083)</span></td></tr></table><blockquote><p><b>package</b></p><p><b>type</b>: Box <span style="background: LightGoldenRodYellow; margin: 4px; border: 1px solid khaki"> (100000073346#100000073498)</span></p><p><b>quantity</b>: 1</p><p><b>material</b>: Cardboard <span style="background: LightGoldenRodYellow; margin: 4px; border: 1px solid khaki"> (200000003199#200000003529)</span></p><h3>ShelfLifeStorages</h3><table class="grid"><tr><td>-</td><td><b>Type</b></td><td><b>Period[x]</b></td><td><b>SpecialPrecautionsForStorage</b></td></tr><tr><td>*</td><td>Shelf life of the medicinal product as packaged for sale <span style="background: LightGoldenRodYellow; margin: 4px; border: 1px solid khaki"> (100000073343#100000073403)</span></td><td>2 Year<span style="background: LightGoldenRodYellow"> (Details: http://spor.ema.europa.eu/v1/lists/100000110633 code 200000003434 = '200000003434')</span></td><td>Do not store above 30 °C <span style="background: LightGoldenRodYellow; margin: 4px; border: 1px solid khaki"> (100000073344#100000073411)</span>, Do not freeze <span style="background: LightGoldenRodYellow; margin: 4px; border: 1px solid khaki"> (100000073344#100000073420)</span>, Do not refrigerate <span style="background: LightGoldenRodYellow; margin: 4px; border: 1px solid khaki"> (100000073344#100000073419)</span></td></tr></table><blockquote><p><b>package</b></p><p><b>type</b>: Single-dose container <span style="background: LightGoldenRodYellow; margin: 4px; border: 1px solid khaki"> (100000073346#100000073550)</span></p><p><b>quantity</b>: 2</p><p><b>material</b>: Plastic <span style="background: LightGoldenRodYellow; margin: 4px; border: 1px solid khaki"> (200000003199#200000003208)</span>, Aluminium <span style="background: LightGoldenRodYellow; margin: 4px; border: 1px solid khaki"> (200000003199#200000003200)</span></p></blockquote></blockquote></div>
        </text>
        <extension url="http://ema.europa.eu/fhir/extension/containedItemQuantity">
          <valueQuantity>
            <value value="2"/>
            <unit value="Plaster"/>
            <system value="http://spor.ema.europa.eu/v1/lists/200000000014"/>
            <code value="200000002140"/>
          </valueQuantity>
        </extension>
        <packageFor>
          <reference value="MedicinalProductDefinition/EMLA-2525-Plaster-SE-AJ-MedicinalProductDefinition"/>
        </packageFor>
        <description value="Påse, 2 x 1 plåster">
          <extension url="http://ema.europa.eu/fhir/extension/language">
            <valueCoding>
              <system value="http://spor.ema.europa.eu/v1/lists/100000072057"/>
              <code value="100000072288"/>
              <display value="Swedish"/>
            </valueCoding>
          </extension>
        </description>
        <marketingStatus>
          <country>
            <coding>
              <system value="http://spor.ema.europa.eu/v1/lists/100000000002"/>
              <code value="100000000535"/>
              <display value="Sweden"/>
            </coding>
          </country>
          <status>
            <coding>
              <system value="http://spor.ema.europa.eu/v1/lists/100000072052"/>
              <code value="100000072083"/>
              <display value="Marketed"/>
            </coding>
          </status>
        </marketingStatus>
        <package>
          <type>
            <coding>
              <system value="http://spor.ema.europa.eu/v1/lists/100000073346"/>
              <code value="100000073498"/>
              <display value="Box"/>
            </coding>
          </type>
          <quantity value="1"/>
          <material>
            <coding>
              <system value="http://spor.ema.europa.eu/v1/lists/200000003199"/>
              <code value="200000003529"/>
              <display value="Cardboard"/>
            </coding>
          </material>
          <shelfLifeStorage>
            <type>
              <coding>
                <system value="http://spor.ema.europa.eu/v1/lists/100000073343"/>
                <code value="100000073403"/>
                <display value="Shelf life of the medicinal product as packaged for sale"/>
              </coding>
            </type>
            <periodDuration>
              <value value="2"/>
              <unit value="Year"/>
              <system value="http://spor.ema.europa.eu/v1/lists/100000110633"/>
              <code value="200000003434"/>
            </periodDuration>
            <specialPrecautionsForStorage>
              <coding>
                <system value="https://spor.ema.europa.eu/v1/lists/100000073344"/>
                <code value="100000073411"/>
                <display value="Do not store above 30 °C"/>
              </coding>
            </specialPrecautionsForStorage>
            <specialPrecautionsForStorage>
              <coding>
                <system value="https://spor.ema.europa.eu/v1/lists/100000073344"/>
                <code value="100000073420"/>
                <display value="Do not freeze"/>
              </coding>
            </specialPrecautionsForStorage>
            <specialPrecautionsForStorage>
              <coding>
                <system value="https://spor.ema.europa.eu/v1/lists/100000073344"/>
                <code value="100000073419"/>
                <display value="Do not refrigerate"/>
              </coding>
            </specialPrecautionsForStorage>
          </shelfLifeStorage>
          <package>
            <type>
              <coding>
                <system value="http://spor.ema.europa.eu/v1/lists/100000073346"/>
                <code value="100000073550"/>
                <display value="Single-dose container"/>
              </coding>
            </type>
            <quantity value="2"/>
            <material>
              <coding>
                <system value="http://spor.ema.europa.eu/v1/lists/200000003199"/>
                <code value="200000003208"/>
                <display value="Plastic"/>
              </coding>
            </material>
            <material>
              <coding>
                <system value="http://spor.ema.europa.eu/v1/lists/200000003199"/>
                <code value="200000003200"/>
                <display value="Aluminium"/>
              </coding>
            </material>
            <containedItem>
              <item>
                <reference>
                  <reference value="ManufacturedItemDefinition/EMLA-2525-Plaster-SE-AJ-ManufacturedItemDefinition"/>
                </reference>
              </item>
              <amount>
                <value value="1"/>
                <unit value="plaster"/>
                <system value="http://spor.ema.europa.eu/v1/lists/200000000014"/>
                <code value="200000002140"/>
              </amount>
            </containedItem>
          </package>
        </package>
      </PackagedProductDefinition>
    </resource>
    <request>
      <method value="POST"/>
      <url value="PackagedProductDefinition/EMLA-2525-Plaster-SE-AJ-PackagedProductDefinition01"/>
    </request>
  </entry>
  <entry>
    <fullUrl value="{$base}/PackagedProductDefinition/EMLA-2525-Plaster-SE-AJ-PackagedProductDefinition02"/>
    <resource>
      <PackagedProductDefinition>
        <id value="EMLA-2525-Plaster-SE-AJ-PackagedProductDefinition02"/>
        <text>
          <status value="generated"/><div xmlns="http://www.w3.org/1999/xhtml"><p><b>Generated Narrative: PackagedProductDefinition</b><a name="EMLA-2525-Plaster-SE-AJ-PackagedProductDefinition02"> </a></p><div style="display: inline-block; background-color: #d9e0e7; padding: 6px; margin: 4px; border: 1px solid #8da1b4; border-radius: 5px; line-height: 60%"><p style="margin-bottom: 0px">Resource PackagedProductDefinition &quot;EMLA-2525-Plaster-SE-AJ-PackagedProductDefinition02&quot; </p></div><p><b>packageFor</b>: <a href="#MedicinalProductDefinition_EMLA-2525-Plaster-SE-AJ-MedicinalProductDefinition">See above (MedicinalProductDefinition/EMLA-2525-Plaster-SE-AJ-MedicinalProductDefinition)</a></p><p><b>description</b>: Påse, 20 x 1 plåster</p><h3>MarketingStatuses</h3><table class="grid"><tr><td>-</td><td><b>Country</b></td><td><b>Status</b></td></tr><tr><td>*</td><td>Sweden <span style="background: LightGoldenRodYellow; margin: 4px; border: 1px solid khaki"> (100000000002#100000000535)</span></td><td>Marketed <span style="background: LightGoldenRodYellow; margin: 4px; border: 1px solid khaki"> (100000072052#100000072083)</span></td></tr></table><blockquote><p><b>package</b></p><p><b>type</b>: Box <span style="background: LightGoldenRodYellow; margin: 4px; border: 1px solid khaki"> (100000073346#100000073498)</span></p><p><b>quantity</b>: 1</p><p><b>material</b>: Cardboard <span style="background: LightGoldenRodYellow; margin: 4px; border: 1px solid khaki"> (200000003199#200000003529)</span></p><h3>ShelfLifeStorages</h3><table class="grid"><tr><td>-</td><td><b>Type</b></td><td><b>Period[x]</b></td><td><b>SpecialPrecautionsForStorage</b></td></tr><tr><td>*</td><td>Shelf life of the medicinal product as packaged for sale <span style="background: LightGoldenRodYellow; margin: 4px; border: 1px solid khaki"> (100000073343#100000073403)</span></td><td>2 Year<span style="background: LightGoldenRodYellow"> (Details: http://spor.ema.europa.eu/v1/lists/100000110633 code 200000003434 = '200000003434')</span></td><td>Do not store above 30 °C <span style="background: LightGoldenRodYellow; margin: 4px; border: 1px solid khaki"> (100000073344#100000073411)</span>, Do not freeze <span style="background: LightGoldenRodYellow; margin: 4px; border: 1px solid khaki"> (100000073344#100000073420)</span>, Do not refrigerate <span style="background: LightGoldenRodYellow; margin: 4px; border: 1px solid khaki"> (100000073344#100000073419)</span></td></tr></table><blockquote><p><b>package</b></p><p><b>type</b>: Single-dose container <span style="background: LightGoldenRodYellow; margin: 4px; border: 1px solid khaki"> (100000073346#100000073550)</span></p><p><b>quantity</b>: 20</p><p><b>material</b>: Plastic <span style="background: LightGoldenRodYellow; margin: 4px; border: 1px solid khaki"> (200000003199#200000003208)</span>, Aluminium <span style="background: LightGoldenRodYellow; margin: 4px; border: 1px solid khaki"> (200000003199#200000003200)</span></p></blockquote></blockquote></div>
        </text>
        <extension url="http://ema.europa.eu/fhir/extension/containedItemQuantity">
          <valueQuantity>
            <value value="20"/>
            <unit value="Plaster"/>
            <system value="http://spor.ema.europa.eu/v1/lists/200000000014"/>
            <code value="200000002140"/>
          </valueQuantity>
        </extension>
        <packageFor>
          <reference value="MedicinalProductDefinition/EMLA-2525-Plaster-SE-AJ-MedicinalProductDefinition"/>
        </packageFor>
        <description value="Påse, 20 x 1 plåster">
          <extension url="http://ema.europa.eu/fhir/extension/language">
            <valueCoding>
              <system value="http://spor.ema.europa.eu/v1/lists/100000072057"/>
              <code value="100000072288"/>
              <display value="Swedish"/>
            </valueCoding>
          </extension>
        </description>
        <marketingStatus>
          <country>
            <coding>
              <system value="http://spor.ema.europa.eu/v1/lists/100000000002"/>
              <code value="100000000535"/>
              <display value="Sweden"/>
            </coding>
          </country>
          <status>
            <coding>
              <system value="http://spor.ema.europa.eu/v1/lists/100000072052"/>
              <code value="100000072083"/>
              <display value="Marketed"/>
            </coding>
          </status>
        </marketingStatus>
        <package>
          <type>
            <coding>
              <system value="http://spor.ema.europa.eu/v1/lists/100000073346"/>
              <code value="100000073498"/>
              <display value="Box"/>
            </coding>
          </type>
          <quantity value="1"/>
          <material>
            <coding>
              <system value="http://spor.ema.europa.eu/v1/lists/200000003199"/>
              <code value="200000003529"/>
              <display value="Cardboard"/>
            </coding>
          </material>
          <shelfLifeStorage>
            <type>
              <coding>
                <system value="http://spor.ema.europa.eu/v1/lists/100000073343"/>
                <code value="100000073403"/>
                <display value="Shelf life of the medicinal product as packaged for sale"/>
              </coding>
            </type>
            <periodDuration>
              <value value="2"/>
              <unit value="Year"/>
              <system value="http://spor.ema.europa.eu/v1/lists/100000110633"/>
              <code value="200000003434"/>
            </periodDuration>
            <specialPrecautionsForStorage>
              <coding>
                <system value="https://spor.ema.europa.eu/v1/lists/100000073344"/>
                <code value="100000073411"/>
                <display value="Do not store above 30 °C"/>
              </coding>
            </specialPrecautionsForStorage>
            <specialPrecautionsForStorage>
              <coding>
                <system value="https://spor.ema.europa.eu/v1/lists/100000073344"/>
                <code value="100000073420"/>
                <display value="Do not freeze"/>
              </coding>
            </specialPrecautionsForStorage>
            <specialPrecautionsForStorage>
              <coding>
                <system value="https://spor.ema.europa.eu/v1/lists/100000073344"/>
                <code value="100000073419"/>
                <display value="Do not refrigerate"/>
              </coding>
            </specialPrecautionsForStorage>
          </shelfLifeStorage>
          <package>
            <type>
              <coding>
                <system value="http://spor.ema.europa.eu/v1/lists/100000073346"/>
                <code value="100000073550"/>
                <display value="Single-dose container"/>
              </coding>
            </type>
            <quantity value="20"/>
            <material>
              <coding>
                <system value="http://spor.ema.europa.eu/v1/lists/200000003199"/>
                <code value="200000003208"/>
                <display value="Plastic"/>
              </coding>
            </material>
            <material>
              <coding>
                <system value="http://spor.ema.europa.eu/v1/lists/200000003199"/>
                <code value="200000003200"/>
                <display value="Aluminium"/>
              </coding>
            </material>
            <containedItem>
              <item>
                <reference>
                  <reference value="ManufacturedItemDefinition/EMLA-2525-Plaster-SE-AJ-ManufacturedItemDefinition"/>
                </reference>
              </item>
              <amount>
                <value value="1"/>
                <unit value="plaster"/>
                <system value="http://spor.ema.europa.eu/v1/lists/200000000014"/>
                <code value="200000002140"/>
              </amount>
            </containedItem>
          </package>
        </package>
      </PackagedProductDefinition>
    </resource>
    <request>
      <method value="POST"/>
      <url value="PackagedProductDefinition/EMLA-2525-Plaster-SE-AJ-PackagedProductDefinition02"/>
    </request>
  </entry>
  <entry>
    <fullUrl value="{$base}/ManufacturedItemDefinition/EMLA-2525-Plaster-SE-AJ-ManufacturedItemDefinition"/>
    <resource>
      <ManufacturedItemDefinition>
        <id value="EMLA-2525-Plaster-SE-AJ-ManufacturedItemDefinition"/>
        <text>
          <status value="generated"/><div xmlns="http://www.w3.org/1999/xhtml"><p><b>Generated Narrative: ManufacturedItemDefinition</b><a name="EMLA-2525-Plaster-SE-AJ-ManufacturedItemDefinition"> </a></p><div style="display: inline-block; background-color: #d9e0e7; padding: 6px; margin: 4px; border: 1px solid #8da1b4; border-radius: 5px; line-height: 60%"><p style="margin-bottom: 0px">Resource ManufacturedItemDefinition &quot;EMLA-2525-Plaster-SE-AJ-ManufacturedItemDefinition&quot; </p></div><p><b>status</b>: active</p><p><b>manufacturedDoseForm</b>: Medicated plaster <span style="background: LightGoldenRodYellow; margin: 4px; border: 1px solid khaki"> (200000000004#100000073714)</span></p><p><b>unitOfPresentation</b>: plaster <span style="background: LightGoldenRodYellow; margin: 4px; border: 1px solid khaki"> (200000000014#200000002140)</span></p></div>
        </text>
        <status value="active"/>
        <manufacturedDoseForm>
          <coding>
            <system value="http://spor.ema.europa.eu/v1/lists/200000000004"/>
            <code value="100000073714"/>
            <display value="Medicated plaster"/>
          </coding>
        </manufacturedDoseForm>
        <unitOfPresentation>
          <coding>
            <system value="http://spor.ema.europa.eu/v1/lists/200000000014"/>
            <code value="200000002140"/>
            <display value="plaster"/>
          </coding>
        </unitOfPresentation>
      </ManufacturedItemDefinition>
    </resource>
    <request>
      <method value="POST"/>
      <url value="ManufacturedItemDefinition/EMLA-2525-Plaster-SE-AJ-ManufacturedItemDefinition"/>
    </request>
  </entry>
  <entry>
    <fullUrl value="{$base}/Ingredient/EMLA-2525-Plaster-SE-AJ-Ingredient01"/>
    <resource>
      <Ingredient>
        <id value="EMLA-2525-Plaster-SE-AJ-Ingredient01"/>
        <text>
          <status value="generated"/><div xmlns="http://www.w3.org/1999/xhtml"><p><b>Generated Narrative: Ingredient</b><a name="EMLA-2525-Plaster-SE-AJ-Ingredient01"> </a></p><div style="display: inline-block; background-color: #d9e0e7; padding: 6px; margin: 4px; border: 1px solid #8da1b4; border-radius: 5px; line-height: 60%"><p style="margin-bottom: 0px">Resource Ingredient &quot;EMLA-2525-Plaster-SE-AJ-Ingredient01&quot; </p></div><p><b>status</b>: active</p><p><b>for</b>: </p><ul><li><a href="#MedicinalProductDefinition_EMLA-2525-Plaster-SE-AJ-MedicinalProductDefinition">See above (MedicinalProductDefinition/EMLA-2525-Plaster-SE-AJ-MedicinalProductDefinition)</a></li><li><a href="#ManufacturedItemDefinition_EMLA-2525-Plaster-SE-AJ-ManufacturedItemDefinition">See above (ManufacturedItemDefinition/EMLA-2525-Plaster-SE-AJ-ManufacturedItemDefinition)</a></li><li><a href="#AdministrableProductDefinition_EMLA-2525-Plaster-SE-AJ-AdministrableProductDefinition">See above (AdministrableProductDefinition/EMLA-2525-Plaster-SE-AJ-AdministrableProductDefinition)</a></li></ul><p><b>role</b>: Active <span style="background: LightGoldenRodYellow; margin: 4px; border: 1px solid khaki"> (100000072050#100000072072)</span></p><blockquote><p><b>substance</b></p><h3>Codes</h3><table class="grid"><tr><td>-</td><td><b>Concept</b></td></tr><tr><td>*</td><td>lidocaine <span style="background: LightGoldenRodYellow; margin: 4px; border: 1px solid khaki"> (SubstanceDefinition#100000091713)</span></td></tr></table><blockquote><p><b>strength</b></p><p><b>presentation</b>: 25 milligram(s)<span style="background: LightGoldenRodYellow"> (Details: https://spor.ema.europa.eu/v1/lists/100000110633 code 100000110655 = '100000110655')</span>/1 plaster<span style="background: LightGoldenRodYellow"> (Details: https://spor.ema.europa.eu/v1/lists/200000000014 code 200000002140 = '200000002140')</span></p><blockquote><p><b>referenceStrength</b></p><h3>Substances</h3><table class="grid"><tr><td>-</td><td><b>Concept</b></td></tr><tr><td>*</td><td>lidocaine <span style="background: LightGoldenRodYellow; margin: 4px; border: 1px solid khaki"> (SubstanceDefinition#100000091713)</span></td></tr></table><p><b>strength</b>: 25 milligram(s)<span style="background: LightGoldenRodYellow"> (Details: https://spor.ema.europa.eu/v1/lists/100000110633 code 100000110655 = '100000110655')</span>/1 plaster<span style="background: LightGoldenRodYellow"> (Details: https://spor.ema.europa.eu/v1/lists/200000000014 code 200000002140 = '200000002140')</span></p></blockquote></blockquote></blockquote></div>
        </text>
        <status value="active"/>
        <for>
          <reference value="MedicinalProductDefinition/EMLA-2525-Plaster-SE-AJ-MedicinalProductDefinition"/>
        </for>
        <for>
          <reference value="ManufacturedItemDefinition/EMLA-2525-Plaster-SE-AJ-ManufacturedItemDefinition"/>
        </for>
        <for>
          <reference value="AdministrableProductDefinition/EMLA-2525-Plaster-SE-AJ-AdministrableProductDefinition"/>
        </for>
        <role>
          <coding>
            <system value="http://spor.ema.europa.eu/v1/lists/100000072050"/>
            <code value="100000072072"/>
            <display value="Active"/>
          </coding>
        </role>
        <substance>
          <code>
            <concept>
              <coding>
                <system value="https://spor.ema.europa.eu/v2/SubstanceDefinition"/>
                <code value="100000091713"/>
                <display value="lidocaine"/>
              </coding>
            </concept>
          </code>
          <strength>
            <presentationRatio>
              <numerator>
                <value value="25"/>
                <unit value="milligram(s)"/>
                <system value="https://spor.ema.europa.eu/v1/lists/100000110633"/>
                <code value="100000110655"/>
              </numerator>
              <denominator>
                <value value="1"/>
                <unit value="plaster"/>
                <system value="https://spor.ema.europa.eu/v1/lists/200000000014"/>
                <code value="200000002140"/>
              </denominator>
            </presentationRatio>
            <referenceStrength>
              <substance>
                <concept>
                  <coding>
                    <system value="https://spor.ema.europa.eu/v2/SubstanceDefinition"/>
                    <code value="100000091713"/>
                    <display value="lidocaine"/>
                  </coding>
                </concept>
              </substance>
              <strengthRatio>
                <numerator>
                  <value value="25"/>
                  <unit value="milligram(s)"/>
                  <system value="https://spor.ema.europa.eu/v1/lists/100000110633"/>
                  <code value="100000110655"/>
                </numerator>
                <denominator>
                  <value value="1"/>
                  <unit value="plaster"/>
                  <system value="https://spor.ema.europa.eu/v1/lists/200000000014"/>
                  <code value="200000002140"/>
                </denominator>
              </strengthRatio>
            </referenceStrength>
          </strength>
        </substance>
      </Ingredient>
    </resource>
    <request>
      <method value="POST"/>
      <url value="Ingredient/EMLA-2525-Plaster-SE-AJ-Ingredient01"/>
    </request>
  </entry>
  <entry>
    <fullUrl value="{$base}/Ingredient/EMLA-2525-Plaster-SE-AJ-Ingredient02"/>
    <resource>
      <Ingredient>
        <id value="EMLA-2525-Plaster-SE-AJ-Ingredient02"/>
        <text>
          <status value="generated"/><div xmlns="http://www.w3.org/1999/xhtml"><p><b>Generated Narrative: Ingredient</b><a name="EMLA-2525-Plaster-SE-AJ-Ingredient02"> </a></p><div style="display: inline-block; background-color: #d9e0e7; padding: 6px; margin: 4px; border: 1px solid #8da1b4; border-radius: 5px; line-height: 60%"><p style="margin-bottom: 0px">Resource Ingredient &quot;EMLA-2525-Plaster-SE-AJ-Ingredient02&quot; </p></div><p><b>status</b>: active</p><p><b>for</b>: </p><ul><li><a href="#MedicinalProductDefinition_EMLA-2525-Plaster-SE-AJ-MedicinalProductDefinition">See above (MedicinalProductDefinition/EMLA-2525-Plaster-SE-AJ-MedicinalProductDefinition)</a></li><li><a href="#ManufacturedItemDefinition_EMLA-2525-Plaster-SE-AJ-ManufacturedItemDefinition">See above (ManufacturedItemDefinition/EMLA-2525-Plaster-SE-AJ-ManufacturedItemDefinition)</a></li><li><a href="#AdministrableProductDefinition_EMLA-2525-Plaster-SE-AJ-AdministrableProductDefinition">See above (AdministrableProductDefinition/EMLA-2525-Plaster-SE-AJ-AdministrableProductDefinition)</a></li></ul><p><b>role</b>: Active <span style="background: LightGoldenRodYellow; margin: 4px; border: 1px solid khaki"> (100000072050#100000072072)</span></p><blockquote><p><b>substance</b></p><h3>Codes</h3><table class="grid"><tr><td>-</td><td><b>Concept</b></td></tr><tr><td>*</td><td>Prilocaine <span style="background: LightGoldenRodYellow; margin: 4px; border: 1px solid khaki"> (SubstanceDefinition#100000092015)</span></td></tr></table><blockquote><p><b>strength</b></p><p><b>presentation</b>: 25 milligram(s)<span style="background: LightGoldenRodYellow"> (Details: https://spor.ema.europa.eu/v1/lists/100000110633 code 100000110655 = '100000110655')</span>/1 plaster<span style="background: LightGoldenRodYellow"> (Details: https://spor.ema.europa.eu/v1/lists/200000000014 code 200000002140 = '200000002140')</span></p><blockquote><p><b>referenceStrength</b></p><h3>Substances</h3><table class="grid"><tr><td>-</td><td><b>Concept</b></td></tr><tr><td>*</td><td>Prilocaine <span style="background: LightGoldenRodYellow; margin: 4px; border: 1px solid khaki"> (SubstanceDefinition#100000092015)</span></td></tr></table><p><b>strength</b>: 25 milligram(s)<span style="background: LightGoldenRodYellow"> (Details: https://spor.ema.europa.eu/v1/lists/100000110633 code 100000110655 = '100000110655')</span>/1 plaster<span style="background: LightGoldenRodYellow"> (Details: https://spor.ema.europa.eu/v1/lists/200000000014 code 200000002140 = '200000002140')</span></p></blockquote></blockquote></blockquote></div>
        </text>
        <status value="active"/>
        <for>
          <reference value="MedicinalProductDefinition/EMLA-2525-Plaster-SE-AJ-MedicinalProductDefinition"/>
        </for>
        <for>
          <reference value="ManufacturedItemDefinition/EMLA-2525-Plaster-SE-AJ-ManufacturedItemDefinition"/>
        </for>
        <for>
          <reference value="AdministrableProductDefinition/EMLA-2525-Plaster-SE-AJ-AdministrableProductDefinition"/>
        </for>
        <role>
          <coding>
            <system value="http://spor.ema.europa.eu/v1/lists/100000072050"/>
            <code value="100000072072"/>
            <display value="Active"/>
          </coding>
        </role>
        <substance>
          <code>
            <concept>
              <coding>
                <system value="https://spor.ema.europa.eu/v2/SubstanceDefinition"/>
                <code value="100000092015"/>
                <display value="Prilocaine"/>
              </coding>
            </concept>
          </code>
          <strength>
            <presentationRatio>
              <numerator>
                <value value="25"/>
                <unit value="milligram(s)"/>
                <system value="https://spor.ema.europa.eu/v1/lists/100000110633"/>
                <code value="100000110655"/>
              </numerator>
              <denominator>
                <value value="1"/>
                <unit value="plaster"/>
                <system value="https://spor.ema.europa.eu/v1/lists/200000000014"/>
                <code value="200000002140"/>
              </denominator>
            </presentationRatio>
            <referenceStrength>
              <substance>
                <concept>
                  <coding>
                    <system value="https://spor.ema.europa.eu/v2/SubstanceDefinition"/>
                    <code value="100000092015"/>
                    <display value="Prilocaine"/>
                  </coding>
                </concept>
              </substance>
              <strengthRatio>
                <numerator>
                  <value value="25"/>
                  <unit value="milligram(s)"/>
                  <system value="https://spor.ema.europa.eu/v1/lists/100000110633"/>
                  <code value="100000110655"/>
                </numerator>
                <denominator>
                  <value value="1"/>
                  <unit value="plaster"/>
                  <system value="https://spor.ema.europa.eu/v1/lists/200000000014"/>
                  <code value="200000002140"/>
                </denominator>
              </strengthRatio>
            </referenceStrength>
          </strength>
        </substance>
      </Ingredient>
    </resource>
    <request>
      <method value="POST"/>
      <url value="Ingredient/EMLA-2525-Plaster-SE-AJ-Ingredient02"/>
    </request>
  </entry>
</Bundle>